paniniwikiparser/__init__.py
paniniwikiparser/__main__.py
paniniwikiparser/wiki/__init__.py
paniniwikiparser/wiki/common/__init__.py
paniniwikiparser/wiki/common/error_log.py
paniniwikiparser/wiki/common/preprocesstext.py
paniniwikiparser/wiki/data/__init__.py
paniniwikiparser/wiki/data/extractor.py
paniniwikiparser/wiki/db/__init__.py
paniniwikiparser/wiki/db/db_config.py
paniniwikiparser/wiki/db/dbinsertion.py
paniniwikiparser-0.0.8.dist-info/LICENSE
paniniwikiparser-0.0.8.dist-info/METADATA
paniniwikiparser-0.0.8.dist-info/WHEEL
paniniwikiparser-0.0.8.dist-info/top_level.txt
paniniwikiparser-0.0.8.dist-info/RECORD
